tibian/__init__.py
tibian/config.py
tibian/main.py
tibian/sources/__init__.py
tibian/sources/jira.py
tibian/sources/ticketsource.py
tibian/targets/__init__.py
tibian/targets/stdout.py
tibian/targets/target.py
tibian/targets/teams.py
tibian/tickets.py
tibian/vars.py
tibian-1.1.0.dist-info/LICENSE
tibian-1.1.0.dist-info/METADATA
tibian-1.1.0.dist-info/WHEEL
tibian-1.1.0.dist-info/entry_points.txt
tibian-1.1.0.dist-info/RECORD
