Metadata-Version: 2.1
Name: tibian
Version: 1.1.0
Summary: Ticket birthday announcer: A package to announce all creation birthdays of your tickets that live (too) long enough
Home-page: https://github.com/Alicipy/tibian
License: MIT
Keywords: agile,jira,birthdays
Author: Stefan Kraus
Author-email: dev@stefankraus.org
Requires-Python: >=3.9,<4.0
Classifier: License :: OSI Approved :: MIT License
Classifier: Programming Language :: Python :: 3
Classifier: Programming Language :: Python :: 3.9
Classifier: Programming Language :: Python :: 3.10
Classifier: Programming Language :: Python :: 3.11
Classifier: Programming Language :: Python :: 3.12
Requires-Dist: PyYAML (>=6.0,<7.0)
Requires-Dist: jira (>=3.1.1,<4.0.0)
Requires-Dist: python-dateutil (>=2.8.2,<3.0.0)
Requires-Dist: requests (>=2.27.1,<3.0.0)
Project-URL: Repository, https://github.com/Alicipy/tibian
